ans_project/__init__.py
ans_project/sdk/__init__.py
ans_project/sdk/cli.py
ans_project/sdk/client.py
ans_project/sdk/models.py
ans_project_sdk-0.0.6.dist-info/licenses/LICENSE
ans_project_sdk-0.0.6.dist-info/METADATA
ans_project_sdk-0.0.6.dist-info/WHEEL
ans_project_sdk-0.0.6.dist-info/entry_points.txt
ans_project_sdk-0.0.6.dist-info/top_level.txt
ans_project_sdk-0.0.6.dist-info/RECORD
