Metadata-Version: 2.4
Name: ans-project-sdk
Version: 0.0.6
Summary: Python SDK for the Agent Network System (ANS)
Home-page: https://github.com/g-clouds/ANS/tree/main/sdk/sdk-python
Author: gClouds R&D | gLabs
Keywords: ans,agent,sdk,cli,lookup,discovery,ai-agent
Classifier: Programming Language :: Python :: 3
Classifier: Operating System :: OS Independent
Requires-Python: >=3.7
License-File: LICENSE
Requires-Dist: requests
Requires-Dist: cryptography
Requires-Dist: pydantic
Dynamic: author
Dynamic: classifier
Dynamic: description
Dynamic: description-content-type
Dynamic: home-page
Dynamic: keywords
Dynamic: license-file
Dynamic: requires-dist
Dynamic: requires-python
Dynamic: summary
